nqr_blochsimulator/__init__.py
nqr_blochsimulator/classes/pulse.py
nqr_blochsimulator/classes/sample.py
nqr_blochsimulator/classes/simulation.py
nqr_blochsimulator-0.0.3.dist-info/METADATA
nqr_blochsimulator-0.0.3.dist-info/WHEEL
nqr_blochsimulator-0.0.3.dist-info/licenses/LICENSE
nqr_blochsimulator-0.0.3.dist-info/RECORD
