Metadata-Version: 2.4
Name: nqr_blochsimulator
Version: 0.0.3
Summary: Simple Python script to simulate NQR Bloch equations
Project-URL: Homepage, https://nqrduck.cool
Project-URL: Bug Tracker, https://git.private.coffee/nqrduck/nqr-blochsimulator/issues
Project-URL: Source Code, https://git.private.coffee/nqrduck/nqrduck-blochsimulator
Author-email: jupfi <support@nqrduck.cool>
License: MIT License
License-File: LICENSE
Classifier: License :: OSI Approved :: MIT License
Classifier: Operating System :: OS Independent
Classifier: Programming Language :: Python :: 3
Requires-Python: >=3.10
Requires-Dist: matplotlib
Requires-Dist: numpy
Requires-Dist: scipy
